sergiu_presentation/__init__.py
sergiu_presentation/sergiu.py
sergiu_presentation-0.1.4.dist-info/METADATA
sergiu_presentation-0.1.4.dist-info/WHEEL
sergiu_presentation-0.1.4.dist-info/top_level.txt
sergiu_presentation-0.1.4.dist-info/RECORD
