Metadata-Version: 2.1
Name: sergiu-presentation
Version: 0.1.4
Summary: Demo library
Home-page: UNKNOWN
Author: Matei Sergiu-Răzvan
Author-email: mateisergiu777@gmail.com
License: UNKNOWN
Platform: UNKNOWN
